rstatspy.cpython-312-x86_64-linux-musl.so
rstatspy-0.1.0.dist-info/RECORD
rstatspy-0.1.0.dist-info/WHEEL
rstatspy-0.1.0.dist-info/METADATA
rstatspy-0.1.0.dist-info/licenses/LICENSE.txt
lib/librstats.so
lib/cmake/rstats/rstatsConfig-release.cmake
lib/cmake/rstats/rstatsConfig.cmake
include/rstats.h
