Metadata-Version: 2.1
Name: rstatspy
Version: 0.1.0
